Workbook

Sheet Cotización
A1: COTIZACIÓN ETAPA 1 - VIVIENDA UNIFAMILIAR, CHORRILLOS
A2: Cimentación, columnas 1er piso hasta +2.30, cerco delantero y muros del perímetro (E-10). Precios Lima, octubre 2026.
A4: Concepto | B4: Monto (S/) | C4: % | D4: Quién paga
A5: A. Materiales | B5: =Materiales!$F$32 -> 52798.19 | C5: =B5/$B$10 -> 0.58090943 | D5: Cliente - compra directa con boleta/factura
A6: B. Equipos y servicios (volquetes, apisonador, probetas, agua, flete) | B6: ='Equipos y servicios'!$F$11 -> 4715 | C6: =B6/$B$10 -> 0.051876551 | D6: Cliente
A7: C. Mano de obra, retroexcavadora y dirección técnica (por un tanto) | B7: ='Mano de obra'!$F$34 -> 30500 | C7: =B7/$B$10 -> 0.33557472 | D7: Pago por etapas al contratista
A8: SUBTOTAL | B8: =SUM(B5:B7) -> 88013.19 | C8: =B8/$B$10 -> 0.9683607
A9: D. Imprevistos 5% (sobre A + B) | B9: =0.05*(B5+B6) -> 2875.6595 | C9: =B9/$B$10 -> 0.031639299 | D9: Variaciones de precio y de metrado hasta el EMS
A10: TOTAL ETAPA 1 | B10: =B8+B9 -> 90888.849 | C10: =B10/$B$10 -> 1
A11: Adicional: calzaduras (solo si se necesitan, se cotizan aparte) | B11: por definir
A13: FORMA DE PAGO DE LA MANO DE OBRA (por etapa terminada y revisada)
A14: Etapa | B14: Monto (S/) | C14: %
A15: 1. Limpieza, trazo, excavación con máquina, perfilado y eliminación | B15: =$B$7*C15 -> 4575 | C15: 0.15
A16: 2. Solados, acero, encofrado y vaciado de zapatas, VE y VC | B16: =$B$7*C16 -> 9150 | C16: 0.3
A17: 3. Relleno compactado y sobrecimientos | B17: =$B$7*C17 -> 3660 | C17: 0.12
A18: 4. Columnas del 1er piso hasta +2.30 | B18: =$B$7*C18 -> 7015 | C18: 0.23
A19: 5. Cerco delantero, muros del perímetro, juntas y limpieza final | B19: =$B$7*C19 -> 6100 | C19: 0.2
A20: TOTAL | B20: =SUM(B15:B19) -> 30500 | C20: =SUM(C15:C19) -> 1
A22: INCLUYE: todo lo del cuadro E-10 con metrados verificados (hoja Metrados).
A23: NO INCLUYE: vigas y techo del 1er piso, nudos sobre +2.30, tabiques interiores, escalera, falso piso, tarrajeos, instalaciones, fachada existente, licencia, EMS, calzaduras.
A24: Materiales a precio de tienda con IGV; el premezclado y la bomba deben confirmarse con 2-3 concreteras. Validez: 15 días.
A25: Nivel de VE según E-10 (de -1.00 a -0.30 sobre tecnopor). Si se cambia, se ajusta concreto, encofrado y excavación.

Sheet Metrados
A1: ETAPA 1 - METRADOS VERIFICADOS (E-10 vs. revisión)
A2: Revisión del cuadro E-10 contra E-01, E-02/E-03, E-04. Filas en naranja = corregidas. VE de -1.00 a -0.30 sobre tecnopor (zanja de 1.10 de E-10).
A4: Ítem | B4: Partida | C4: Und | D4: Metrado E-10 | E4: Metrado verificado | F4: Diferencia | G4: Sustento de la verificación
A5: 01 OBRAS PRELIMINARES
A6: 01.01 | B6: Limpieza de terreno | C6: m² | D6: 170 | E6: 170 | F6: =E6-D6 -> 0 | G6: Lote 7.90 × 21.55
A7: 01.02 | B7: Trazo, nivelación y replanteo | C7: m² | D7: 170 | E7: 170 | F7: =E7-D7 -> 0 | G7: Lote 7.90 × 21.55
A8: 02 MOVIMIENTO DE TIERRAS
A9: 02.01 | B9: Excavación zapatas vivienda (retroexcavadora) | C9: m³ | D9: 87.1 | E9: 87.1 | F9: =E9-D9 -> 0 | G9: 15 zapatas + 0.10 de sobreancho × 1.60 (fondo -1.50 + solado)
A10: 02.02 | B10: Excavación zanjas VE / VC (retroexcavadora) | C10: m³ | D10: 24.3 | E10: 24.3 | F10: =E10-D10 -> 0 | G10: VE 0.70×1.10×24.53 m = 18.9; VC 0.55×1.50×6.56 m = 5.4
A11: 02.03 | B11: Excavación manual cerco (ZC, cimiento corrido, VA) | C11: m³ | D11: 5 | E11: 13.3 | F11: =E11-D11 -> 8.3 | G11: E-10 omite la VA del cerco. ZC 5.04 + cimiento 2.97 + VA 5.31 (de tu Excel, E-09)
A12: 02.04 | B12: Relleno compactado con material propio hasta -0.20 | C12: m³ | D12: 79.4 | E12: 61.1 | F12: =E12-D12 -> -18.3 | G12: Vivienda: 111.4 excav. - 43.1 enterrado - 14.5 (capa superior 0.20) = 53.8; cerco 7.3. E-10 79.4 NO CABE en la excavación
A13: 02.05 | B13: Eliminación de material excedente (esponj. 25%) | C13: m³ | D13: 53.5 | E13: 79.5 | F13: =E13-D13 -> 26 | G13: (124.7 - 61.1) × 1.25. E-10 sale bajo porque su relleno está inflado
A14: 03 CONCRETO SIMPLE
A15: 03.01 | B15: Solado C:H 1:12 (0.10 vivienda / 0.05 cerco) | C15: m² | D15: 50 | E15: 50 | F15: =E15-D15 -> 0 | G15: 46.79 + 3.20
A16: 03.02 | B16: Cimiento corrido ciclópeo 1:10 + 30% PG (cerco) | C16: m³ | D16: 2.2 | E16: 2.2 | F16: =E16-D16 -> 0 | G16: 9.28 × 0.40 × 0.60
A17: 03.03 | B17: Sobrecimiento 1:8 + 25% PM 0.15×0.40 (perímetro + cerco) | C17: m³ | D17: 2.7 | E17: 2.7 | F17: =E17-D17 -> 0 | G17: (31.7 + 11.8) × 0.15 × 0.40
A18: 03.04 | B18: Encofrado de sobrecimiento (2 caras) | C18: m² | D18: 35.4 | E18: 35.4 | F18: =E18-D18 -> 0 | G18: 43.5 × 0.40 × 2
A19: 04 CONCRETO ARMADO f'c 210
A20: 04.01 | B20: Zapatas Z-1 a Z-5 (vaciado contra terreno) | C20: m³ | D20: 23.4 | E20: 23.4 | F20: =E20-D20 -> 0 | G20: Cuadro E-01
A21: 04.02 | B21: Vigas de equilibrio VE 0.30×0.70 | C21: m³ | D21: 5.2 | E21: 11.65 | F21: =E21-D21 -> 6.45 | G21: E-10 solo mide 24.5 m entre zapatas. Con VE de -1.00 a -0.30 la viga va ENCIMA de la zapata: también se vacía el tramo sobre zapata (30.95 m). 0.21 × 55.47
A22: 04.03 | B22: Encofrado VE (2 caras) | C22: m² | D22: 34.4 | E22: 77.7 | F22: =E22-D22 -> 43.3 | G22: 2 × 0.70 × 55.47 (también sobre la zapata)
A23: 04.04 | B23: Tecnopor e = 0.10 bajo VE (solo entre zapatas) | C23: m² | D23: 7.4 | E23: 7.4 | F23: =E23-D23 -> 0 | G23: 0.30 × 24.53
A24: 04.05 | B24: Vigas de conexión VC 0.25×0.40 | C24: m³ | D24: 0.7 | E24: 0.66 | F24: =E24-D24 -> -0.04 | G24: 0.10 × 6.56 (sobre zapata queda dentro de la zapata)
A25: 04.05b | B25: Encofrado VC | C25: m² | D25: 5.2 | E25: 5.2 | F25: =E25-D25 -> 0 | G25: 2 × 0.40 × 6.56
A26: 04.06 | B26: Columnas 1er piso (-1.00 a +2.30) | C26: m³ | D26: 8.2 | E26: 8.22 | F26: =E26-D26 -> 0.02 | G26: 2.49 m² × 3.30
A27: 04.07 | B27: Encofrado columnas 1er piso | C27: m² | D27: 83.5 | E27: 83.5 | F27: =E27-D27 -> 0 | G27: Perímetros 25.3 m × 3.30
A28: 04.08 | B28: Cerco: ZC, VA, CA, solera | C28: m³ | D28: 3.5 | E28: 3.5 | F28: =E28-D28 -> 0 | G28: E-09 (no verificado: plano no recibido)
A29: 04.08b | B29: Encofrado cerco | C29: m² | D29: 21.9 | E29: 21.9 | F29: =E29-D29 -> 0 | G29: E-09 (no verificado)
A30: 04.09 | B30: Acero fy 4200 habilitado y colocado | C30: kg | D30: 4881 | E30: 5870 | F30: =E30-D30 -> 989 | G30: E-10 pone VE 956 y VC 153 kg. Cuadro de vigas E-02/E-03: VE 1,815 y VC 282 kg (barras continuas con ganchos de 0.45 en columnas)
A31: 04.10 | B31: Anclaje con epóxico Ø3/8" en columnas existentes | C31: und | D31: 8 | E31: 8 | F31: =E31-D31 -> 0
A32: 05 ALBAÑILERÍA KK 18 huecos de soga, mortero 1:4
A33: 05.01 | B33: Muro cerco delantero | C33: m² | D33: 29.8 | E33: 29.8 | F33: =E33-D33 -> 0 | G33: E-09 (no verificado)
A34: 05.02 | B34: Muro perímetro vivienda hasta +2.00 (con junta) | C34: m² | D34: 57.1 | E34: 57.1 | F34: =E34-D34 -> 0 | G34: 31.7 m × 1.80
A35: 05.03 | B35: Junta con tecnopor 1" | C35: ml | D35: 42 | E35: 42 | F35: =E35-D35 -> 0 | G35: Juntas muro-columna × 1.80 + cerco
A36: 06 VARIOS
A37: 06.01 | B37: Curado de concreto | C37: glb | D37: 1 | E37: 1 | F37: =E37-D37 -> 0
A38: 06.02 | B38: Ensayo de probetas | C38: juego | D38: 5 | E38: 5 | F38: =E38-D38 -> 0
A40: IMPORTANTE - NIVEL DE LA VE: E-10 usa VE de -1.00 a -0.30 (zanja de 1.10 y tecnopor debajo). Si la VE va con fondo a -1.50 (al mismo nivel que la zapata),
A41: el concreto de VE baja a 7.0 m³ y el encofrado a 46.7 m², pero la zanja de VE sube a 1.60 de profundidad (27.5 m³). Definir antes de comprar.
A42: Acero de columnas 1er piso: 2,646 kg (E-10) verificado (barras Ø5/8" de 6.00 m de arranque + estribos Ø1/2" 1,342 kg + montaje 3/8" 38 kg).

Sheet Precios
A1: PRECIOS DE MATERIALES Y SERVICIOS - Lima, octubre 2026 (con IGV)
A2: AZUL = editable. Fuente principal: tu Excel (Sodimac / mercado oct-2026). Cambia aquí y todo se recalcula.
A4: Código | B4: Insumo | C4: Und | D4: Precio (S/) | E4: Fuente
A5: prem | B5: Concreto premezclado f'c 210 | C5: m³ | D5: 320 | E5: Mercado Lima S/ 260-320 (tu Excel 300). Se usa 320 por seguridad
A6: bomba | B6: Bomba de concreto | C6: m³ | D6: 38 | E6: S/ 35-40/m³, mínimo 20 m³ por vaciado
A7: cem | B7: Cemento GU / Tipo I 42.5 kg | C7: bolsa | D7: 28.6 | E7: Sodimac oct-2026
A8: are | B8: Arena gruesa | C8: m³ | D8: 65 | E8: Tu Excel
A9: pie | B9: Piedra chancada 1/2" | C9: m³ | D9: 80 | E9: Tu Excel
A10: hor | B10: Hormigón | C10: m³ | D10: 60 | E10: Tu Excel
A11: pg | B11: Piedra grande 6" | C11: m³ | D11: 50 | E11: Tu Excel
A12: pm | B12: Piedra mediana 4" | C12: m³ | D12: 50 | E12: Tu Excel
A13: f34 | B13: Varilla Ø3/4" × 9 m | C13: varilla | D13: 80.02 | E13: Sodimac oct-2026
A14: f58 | B14: Varilla Ø5/8" × 9 m | C14: varilla | D14: 54.41 | E14: Sodimac oct-2026
A15: f12 | B15: Varilla Ø1/2" × 9 m | C15: varilla | D15: 35.96 | E15: Sodimac oct-2026
A16: f38 | B16: Varilla Ø3/8" × 9 m | C16: varilla | D16: 20.06 | E16: Sodimac oct-2026
... A36: encof | B36: Alquiler / reposición de encofrado (tablas, puntales, fenólico) | C36: glb | D36: 2500 | E36: Tu Excel 2,000; +500 por VE sobre zapata

Sheet Materiales
A1: MATERIALES - ETAPA 1 (cantidades por despiece real de varillas)
A2: Concreto estructural con premezclado + bomba. Mezclas menores (solado, ciclópeo, sobrecimiento, solera, mortero) en obra.
A4: N° | B4: Material | C4: Und | D4: Cantidad | E4: P.U. (S/) | F4: Parcial (S/) | G4: Cómo se calculó
A5: A. CONCRETO PREMEZCLADO
A6: 1 | B6: Premezclado f'c 210 - vaciado 1: zapatas + VE + VC + ZC + VA cerco | C6: m³ | D6: 40 | E6: =Precios!$D$5 -> 320 | F6: =D6*E6 -> 12800 | G6: (23.39 + 11.65 + 0.66 + 1.36 + 1.18) × 1.04 = 39.8 → pedir 40.0
A7: 2 | B7: Bomba - vaciado 1 | C7: m³ | D7: 40 | E7: =Precios!$D$6 -> 38 | F7: =D7*E7 -> 1520
A8: 3 | B8: Premezclado f'c 210 - vaciado 2: columnas 1er piso + CA cerco | C8: m³ | D8: 9.5 | E8: =Precios!$D$5 -> 320 | F8: =D8*E8 -> 3040 | G8: (8.22 + 0.60) × 1.04 = 9.2 → pedir 9.5
A9: 4 | B9: Bomba - vaciado 2 (cobra mínimo 20 m³) | C9: m³ | D9: 20 | E9: =Precios!$D$6 -> 38 | F9: =D9*E9 -> 760 | G9: Columnas de 3.30 m: el mixer solo no llega
A10: B. MEZCLAS EN OBRA
A11: 5 | B11: Cemento (solado, ciclópeo, sobrecimiento, solera, mortero) | C11: bolsa | D11: 59 | E11: =Precios!$D$7 -> 28.6 | F11: =D11*E11 -> 1687.4 | G11: Solado 17 + ciclópeo 7 + sobrecim. 11 + solera 4 + mortero 20
A12: 6 | B12: Hormigón (solado, ciclópeo, sobrecimiento) | C12: m³ | D12: 9.6 | E12: =Precios!$D$10 -> 60 | F12: =D12*E12 -> 576 | G12: 5.4 + 1.9 + 2.3
A13: 7 | B13: Arena gruesa (solera + mortero de muros) | C13: m³ | D13: 2.7 | E13: =Precios!$D$8 -> 65 | F13: =D13*E13 -> 175.5 | G13: 0.2 + 87 m² × 0.028
A14: 8 | B14: Piedra chancada 1/2" (solera) | C14: m³ | D14: 0.2 | E14: =Precios!$D$9 -> 80 | F14: =D14*E14 -> 16
A15: 9 | B15: Piedra grande 6" (ciclópeo 30%) | C15: m³ | D15: 1.2 | E15: =Precios!$D$11 -> 50 | F15: =D15*E15 -> 60
A16: 10 | B16: Piedra mediana 4" (sobrecimiento 25%) | C16: m³ | D16: 1.1 | E16: =Precios!$D$12 -> 50 | F16: =D16*E16 -> 55
A17: C. ACERO (por despiece de barras de 9 m, no por kg)
A18: 11 | B18: Varilla Ø3/4" × 9 m | C18: varilla | D18: 72 | E18: =Precios!$D$13 -> 80.02 | F18: =D18*E18 -> 5761.44 | G18: VE en ejes 1-5 continua (8.8 m = 1 varilla por barra): 32; VE en ejes A, B, C: 40
A19: 12 | B19: Varilla Ø5/8" × 9 m | C19: varilla | D19: 207 | E19: =Precios!$D$14 -> 54.41 | F19: =D19*E19 -> 11262.87 | G19: Columnas 136 (arranque 6.00, sobra 3.00 → se usa en zapatas) + zapatas 29 + VE 22 + VC 18 + cerco 2
A20: 13 | B20: Varilla Ø1/2" × 9 m | C20: varilla | D20: 179 | E20: =Precios!$D$15 -> 35.96 | F20: =D20*E20 -> 6436.84 | G20: Estribos columnas 1,342 kg + cerco 177 kg, +5%
A21: 14 | B21: Varilla Ø3/8" × 9 m | C21: varilla | D21: 134 | E21: =Precios!$D$16 -> 20.06 | F21: =D21*E21 -> 2688.04 | G21: Estribos VE 381 und (4 por varilla) 96 + VC 86 und 13 + montaje 9 + cerco 16
A22: 15 | B22: Varilla 6 mm × 9 m | C22: varilla | D22: 15 | E22: =Precios!$D$17 -> 7.96 | F22: =D22*E22 -> 119.4 | G22: Cerco 27 kg
A23: 16 | B23: Alambre N°16 (3% del acero) | C23: rollo | D23: 2 | E23: =Precios!$D$18 -> 349.9 | F23: =D23*E23 -> 699.8 | G23: 176 kg
A24: D. ENCOFRADO Y OTROS
A25: 17 | B25: Alambre N°8 (encofrado) | C25: kg | D25: 56 | E25: =Precios!$D$19 -> 6.5 | F25: =D25*E25 -> 364 | G25: 0.25 kg/m² × 224 m²
A26: 18 | B26: Clavos | C26: kg | D26: 35 | E26: =Precios!$D$20 -> 7.5 | F26: =D26*E26 -> 262.5 | G26: 0.15 kg/m² × 224 m²
A27: 19 | B27: Ladrillo KK 18 huecos (+5%) | C27: und | D27: 3560 | E27: =Precios!$D$21 -> 1.14 | F27: =D27*E27 -> 4058.4 | G27: 86.9 m² × 39 × 1.05
A28: 20 | B28: Tecnopor 4" bajo VE | C28: plancha | D28: 3 | E28: =Precios!$D$22 -> 55 | F28: =D28*E28 -> 165 | G28: 7.4 m² ÷ 2.88
A29: 21 | B29: Tecnopor 1" para juntas | C29: plancha | D29: 5 | E29: =Precios!$D$23 -> 16 | F29: =D29*E29 -> 80 | G29: 12 m² ÷ 2.88
A30: 22 | B30: Epóxico para anclajes | C30: und | D30: 1 | E30: =Precios!$D$24 -> 120 | F30: =D30*E30 -> 120 | G30: 8 anclajes
A31: 23 | B31: Impermeabilizante asfáltico (sobrecimiento) | C31: gal | D31: 2 | E31: =Precios!$D$25 -> 45 | F31: =D31*E31 -> 90
E32: TOTAL | F32: =SUM(F5:F31) -> 52798.19

Sheet Equipos y servicios
A1: EQUIPOS Y SERVICIOS QUE PAGA EL CLIENTE
A4: N° | B4: Concepto | C4: Und | D4: Cantidad | E4: P.U. (S/) | F4: Parcial (S/) | G4: Nota
A5: 1 | B5: Eliminación de desmonte - volquete 18 m³ | C5: viaje | D5: 5 | E5: =Precios!$D$26 -> 460 | F5: =D5*E5 -> 2300 | G5: 79.5 m³ suelto ÷ 18
A6: 2 | B6: Alquiler de apisonador para relleno | C6: día | D6: 8 | E6: =Precios!$D$27 -> 130 | F6: =D6*E6 -> 1040 | G6: 61 m³ ÷ 8 m³/día
A7: 3 | B7: Ensayo de probetas | C7: juego | D7: 5 | E7: =Precios!$D$28 -> 75 | F7: =D7*E7 -> 375 | G7: 1 por vaciado
A8: 4 | B8: Combustible apisonador, trompo y vibrador | C8: gal | D8: 20 | E8: =Precios!$D$29 -> 20 | F8: =D8*E8 -> 400
A9: 5 | B9: Agua para obra | C9: glb | D9: 1 | E9: 300 | F9: =D9*E9 -> 300
A10: 6 | B10: Flete de fierro y agregados | C10: glb | D10: 1 | E10: 300 | F10: =D10*E10 -> 300 | G10: Negociar flete gratis en pedido grande
E11: TOTAL | F11: =SUM(F5:F10) -> 4715

Sheet Mano de obra
A1: MANO DE OBRA "POR UN TANTO" - PRECIO AL CLIENTE
A2: Precio por partida (destajo Lima). La excavación incluye la retroexcavadora y el carguío. Columnas H-J: uso interno (rendimiento de tu cuadrilla operario + ayudante).
A4: Ítem | B4: Partida | C4: Und | D4: Metrado | E4: P.U. MO (S/) | F4: Parcial (S/) | H4: Rend. cuadrilla (und/día) | I4: Días-cuadrilla | J4: Nota
A5: 01.01 | B5: Limpieza de terreno | C5: m² | D5: =Metrados!$E$6 -> 170 | E5: 2 | F5: =D5*E5 -> 340 | H5: 170 | I5: =D5/H5 -> 1
A6: 01.02 | B6: Trazo, nivelación y replanteo | C6: m² | D6: =Metrados!$E$7 -> 170 | E6: 3 | F6: =D6*E6 -> 510 | H6: 170 | I6: =D6/H6 -> 1
A7: 02.01 | B7: Excavación con retroexcavadora (zapatas + zanjas) y carguío | C7: m³ | D7: =Metrados!$E$9+Metrados!$E$10 -> 111.4 | E7: 32 | F7: =D7*E7 -> 3564.8 | H7: - | I7: 0 | J7: Máquina: ver hoja Mi costo
A8: 02.02 | B8: Perfilado y nivelación de fondos | C8: m² | D8: 75.2 | E8: 6 | F8: =D8*E8 -> 451.2 | H8: 25 | I8: =D8/H8 -> 3.008 | J8: Pozos 54.4 + zanjas VE 17.2 + VC 3.6
A9: 02.03 | B9: Excavación manual cerco | C9: m³ | D9: =Metrados!$E$11 -> 13.3 | E9: 45 | F9: =D9*E9 -> 598.5 | H9: 4 | I9: =D9/H9 -> 3.325
A10: 02.04 | B10: Relleno compactado con material propio | C10: m³ | D10: =Metrados!$E$12 -> 61.1 | E10: 30 | F10: =D10*E10 -> 1833 | H10: 8 | I10: =D10/H10 -> 7.6375 | J10: Con apisonador
A11: 03.01 | B11: Solado | C11: m² | D11: =Metrados!$E$15 -> 50 | E11: 15 | F11: =D11*E11 -> 750 | H11: 35 | I11: =D11/H11 -> 1.4285714
A12: 03.02 | B12: Cimiento corrido ciclópeo cerco | C12: m³ | D12: =Metrados!$E$16 -> 2.2 | E12: 90 | F12: =D12*E12 -> 198 | H12: 4 | I12: =D12/H12 -> 0.55
A13: 03.03 | B13: Sobrecimiento - vaciado | C13: m³ | D13: =Metrados!$E$17 -> 2.7 | E13: 120 | F13: =D13*E13 -> 324 | H13: 3 | I13: =D13/H13 -> 0.9
A14: 03.04 | B14: Encofrado y desencofrado de sobrecimiento | C14: m² | D14: =Metrados!$E$18 -> 35.4 | E14: 22 | F14: =D14*E14 -> 778.8 | H14: 14 | I14: =D14/H14 -> 2.5285714
A15: 04.09a | B15: Acero zapatas - habilitado y colocado | C15: kg | D15: 823 | E15: 1.1 | F15: =D15*E15 -> 905.3 | H15: 350 | I15: =D15/H15 -> 2.3514286
A16: 04.09b | B16: Acero VE y VC - habilitado y colocado | C16: kg | D16: 2097 | E16: 1.1 | F16: =D16*E16 -> 2306.7 | H16: 250 | I16: =D16/H16 -> 8.388
A17: 04.03 | B17: Encofrado y desencofrado VE y VC | C17: m² | D17: 82.9 | E17: 25 | F17: =D17*E17 -> 2072.5 | H17: 12 | I17: =D17/H17 -> 6.9083333 | J17: VE 77.7 + VC 5.2
A18: 04.04 | B18: Colocación de tecnopor bajo VE | C18: m² | D18: =Metrados!$E$23 -> 7.4 | E18: 5 | F18: =D18*E18 -> 37 | H18: 50 | I18: =D18/H18 -> 0.148
A19: 04.01 | B19: Vaciado y vibrado premezclado - cimentación (40 m³) | C19: m³ | D19: 38.2 | E19: 40 | F19: =D19*E19 -> 1528 | H19: 38.2 | I19: =D19/H19 -> 1 | J19: 1 día + eventuales
A20: 04.09c | B20: Acero columnas - habilitado y colocado (estribos densos) | C20: kg | D20: 2646 | E20: 1.3 | F20: =D20*E20 -> 3439.8 | H20: 200 | I20: =D20/H20 -> 13.23 | J20: E-10 nota 5: fierrería alta
A21: 04.07 | B21: Encofrado y desencofrado columnas (h = 3.30) | C21: m² | D21: =Metrados!$E$27 -> 83.5 | E21: 28 | F21: =D21*E21 -> 2338 | H21: 10 | I21: =D21/H21 -> 8.35
A22: 04.06 | B22: Vaciado y vibrado premezclado - columnas + CA | C22: m³ | D22: 8.8 | E22: 60 | F22: =D22*E22 -> 528 | H22: 8.8 | I22: =D22/H22 -> 1 | J22: Con bomba, 1 día
A23: 04.09d | B23: Acero cerco | C23: kg | D23: 304 | E23: 1.2 | F23: =D23*E23 -> 364.8 | H23: 150 | I23: =D23/H23 -> 2.0266667
A24: 04.08b | B24: Encofrado y desencofrado cerco | C24: m² | D24: =Metrados!$E$29 -> 21.9 | E24: 25 | F24: =D24*E24 -> 547.5 | H24: 10 | I24: =D24/H24 -> 2.19
A25: 04.08c | B25: Concreto solera cerco (hecho en obra) | C25: m³ | D25: 0.37 | E25: 120 | F25: =D25*E25 -> 44.4 | H25: 2 | I25: =D25/H25 -> 0.185
A26: 04.10 | B26: Anclajes con epóxico | C26: und | D26: =Metrados!$E$31 -> 8 | E26: 20 | F26: =D26*E26 -> 160 | H26: 16 | I26: =D26/H26 -> 0.5
A27: 05.01 | B27: Muro KK de soga - cerco | C27: m² | D27: =Metrados!$E$33 -> 29.8 | E27: 35 | F27: =D27*E27 -> 1043 | H27: 10 | I27: =D27/H27 -> 2.98
A28: 05.02 | B28: Muro KK de soga - perímetro vivienda | C28: m² | D28: =Metrados!$E$34 -> 57.1 | E28: 35 | F28: =D28*E28 -> 1998.5 | H28: 10 | I28: =D28/H28 -> 5.71
A29: 05.03 | B29: Junta con tecnopor 1" | C29: ml | D29: =Metrados!$E$35 -> 42 | E29: 8 | F29: =D29*E29 -> 336 | H29: 60 | I29: =D29/H29 -> 0.7
A30: 06.01 | B30: Curado de concreto (riego diario) | C30: día | D30: 14 | E30: 40 | F30: =D30*E30 -> 560 | H30: 14 | I30: =D30/H30 -> 1 | J30: ≈ 1 h diaria
A31: 06.03 | B31: Limpieza final | C31: glb | D31: 1 | E31: 300 | F31: =D31*E31 -> 300 | H31: 1 | I31: =D31/H31 -> 1
B32: Dirección técnica y residencia de obra (tú) | C32: glb | D32: 1 | E32: 2500 | F32: =D32*E32 -> 2500
E33: TOTAL | F33: =SUM(F5:F32) -> 30357.8 | H33: Total | I33: =SUM(I5:I31) -> 79.045071
E34: A cotizar (redondeado) | F34: =CEILING(F33,500) -> 30500

Sheet INT Mi costo y ganancia
A1: MI COSTO REAL Y GANANCIA COMO CONTRATISTA - HOJA INTERNA, NO ENVIAR
A2: Cuadrilla: 1 operario + 1 ayudante, más tú trabajando y dirigiendo. Jornales informales pagados por día trabajado.
A4: Concepto | B4: Valor | C4: Und / nota
A5: Días-cuadrilla de trabajo (operario + ayudante) | B5: ='Mano de obra'!$I$33 -> 79.045071 | C5: Suma de la hoja Mano de obra
A6: Tu aporte de productividad (trabajando con ellos) | B6: 1.35 | C6: 1.35 = rindes como 1/3 más de cuadrilla (no rindes 100% porque compras, coordinas y supervisas)
A7: Pérdidas, esperas, lluvia/feriados | B7: 0.1 | C7: +10%
A8: DURACIÓN ESTIMADA (días hábiles) | B8: =ROUNDUP(B5/B6*(1+B7),0) -> 65 | C8: Lunes a sábado
A9: Duración en semanas | B9: =B8/6 -> 10.833333 | C9: semanas
A11: COSTOS QUE PAGAS TÚ
A12: Operario: días × jornal | B12: =B8*Precios!$D$32 -> 8450
A13: Ayudante: días × jornal | B13: =B8*Precios!$D$33 -> 5200
A14: Eventuales para vaciados (4 en cimentación + 2 en columnas) | B14: =6*Precios!$D$33 -> 480 | C14: 1 día cada uno
A15: Retroexcavadora: 13 h (mín. 5 h por día) | B15: =13*Precios!$D$30 -> 1950 | C15: Excavación 111 m³ + carguío de 5 volquetes
A16: Traslado de retroexcavadora | B16: =Precios!$D$31 -> 300 | C16: Confirmar si está incluido
A17: Alquiler / reposición de encofrado | B17: =Precios!$D$36 -> 2500
A18: Mezcladora (4 días) y vibrador (2 días) | B18: =4*Precios!$D$34+2*Precios!$D$35 -> 560 | C18: Solados, ciclópeo, sobrecimiento, solera, mortero; vibrado de premezclado
A19: SCTR + EPP (casco, botas, guantes, lentes) | B19: 600 | C19: Obligatorio tenerlo por seguridad
A20: Herramientas menores y consumibles (discos, brocas, baldes) | B20: 400
A21: Movilidad / pasajes propios | B21: 600 | C21: ~10 semanas
A22: TOTAL DE MIS COSTOS | B22: =SUM(B12:B21) -> 21040
A24: COBRO DE MANO DE OBRA AL CLIENTE | B24: ='Mano de obra'!$F$34 -> 30500 | C24: Hoja Mano de obra (redondeado)
A25: MI GANANCIA (incluye pago por mi trabajo y dirección) | B25: =B24-B22 -> 9460
A26: Ganancia por semana | B26: =B25/B9 -> 873.23077 | C26: Compárala con lo que ganarías como operario (~S/ 780/semana)
A27: Margen sobre lo cobrado | B27: =B25/B24 -> 0.31016393
A29: SENSIBILIDAD - si la obra se demora más
A30: Días hábiles reales | B30: Mi ganancia (S/) | C30: Nota
A31: 50 | B31: =B24-(B22-B12-B13+50*(Precios!$D$32+Precios!$D$33)) -> 12610
A32: 60 | B32: =B24-(B22-B12-B13+60*(Precios!$D$32+Precios!$D$33)) -> 10510
A33: 70 | B33: =B24-(B22-B12-B13+70*(Precios!$D$32+Precios!$D$33)) -> 8410
A34: 80 | B34: =B24-(B22-B12-B13+80*(Precios!$D$32+Precios!$D$33)) -> 6310
A35: 90 | B35: =B24-(B22-B12-B13+90*(Precios!$D$32+Precios!$D$33)) -> 4210
